{
    "rules": {
        "adjacent-overload-signatures": true,
        "member-ordering": [
            true,
            {
             "order": "fields-first"
            }
        ],
        "no-internal-module": true,
        "no-namespace": true,
        "no-reference": true,
        "no-var-requires": true,
        "only-arrow-functions": true,
        "prefer-for-of": true,
        "typedef": [
            true,
            "call-signature",
            "arrow-call-signature",
            "parameter",
            "arrow-parameter",
            "property-declaration",
            "variable-declaration",
            "member-variable-declaration"
        ],
        "typedef-whitespace": [
            true,
                {
                "call-signature": "nospace",
                "index-signature": "nospace",
                "parameter": "nospace",
                "property-declaration": "nospace",
                "variable-declaration": "nospace"
            },
            {
                "call-signature": "nospace",
                "index-signature": "nospace",
                "parameter": "nospace",
                "property-declaration": "nospace",
                "variable-declaration": "nospace"
            }
        ],
        "unified-signatures": true
    }
}